{
  "kommunkod": "0305",
  "name": "Håbo",
  "economy": {
    "municipal_tax_pct": {
      "value": 21.59,
      "provenance": {
        "source": "kolada:N00901",
        "period": 2025,
        "fetched": "2026-06-16"
      }
    },
    "total_tax_pct": {
      "value": 33.3,
      "provenance": {
        "source": "kolada:N00900",
        "period": 2025,
        "fetched": "2026-06-16"
      }
    }
  },
  "population": {
    "total": {
      "value": 23252.0,
      "provenance": {
        "source": "kolada:N01951",
        "period": 2025,
        "fetched": "2026-06-16"
      }
    },
    "forecast_change_5y_pct": {
      "value": 2.38632,
      "provenance": {
        "source": "kolada:N02915",
        "period": 2024,
        "fetched": "2026-06-16"
      }
    },
    "forecast_change_10y_pct": {
      "value": 4.81743,
      "provenance": {
        "source": "kolada:N02838",
        "period": 2024,
        "fetched": "2026-06-16"
      }
    }
  }
}