{
  "kommunkod": "0884",
  "name": "Vimmerby",
  "economy": {
    "municipal_tax_pct": {
      "value": 22.36,
      "provenance": {
        "source": "kolada:N00901",
        "period": 2025,
        "fetched": "2026-06-16"
      }
    },
    "total_tax_pct": {
      "value": 34.22,
      "provenance": {
        "source": "kolada:N00900",
        "period": 2025,
        "fetched": "2026-06-16"
      }
    }
  },
  "population": {
    "total": {
      "value": 15327.0,
      "provenance": {
        "source": "kolada:N01951",
        "period": 2025,
        "fetched": "2026-06-16"
      }
    },
    "forecast_change_5y_pct": {
      "value": -2.854336,
      "provenance": {
        "source": "kolada:N02915",
        "period": 2024,
        "fetched": "2026-06-16"
      }
    },
    "forecast_change_10y_pct": {
      "value": -5.101465,
      "provenance": {
        "source": "kolada:N02838",
        "period": 2024,
        "fetched": "2026-06-16"
      }
    }
  }
}