{
  "kommunkod": "1761",
  "name": "Hammarö",
  "economy": {
    "municipal_tax_pct": {
      "value": 22.92,
      "provenance": {
        "source": "kolada:N00901",
        "period": 2025,
        "fetched": "2026-06-16"
      }
    },
    "total_tax_pct": {
      "value": 35.2,
      "provenance": {
        "source": "kolada:N00900",
        "period": 2025,
        "fetched": "2026-06-16"
      }
    }
  },
  "population": {
    "total": {
      "value": 16932.0,
      "provenance": {
        "source": "kolada:N01951",
        "period": 2025,
        "fetched": "2026-06-16"
      }
    },
    "forecast_change_5y_pct": {
      "value": 0.052442,
      "provenance": {
        "source": "kolada:N02915",
        "period": 2024,
        "fetched": "2026-06-16"
      }
    },
    "forecast_change_10y_pct": {
      "value": -0.577916,
      "provenance": {
        "source": "kolada:N02838",
        "period": 2024,
        "fetched": "2026-06-16"
      }
    }
  },
  "jobs": {
    "GazW_2TU_kJw": {
      "label": "Yrken med social inriktning",
      "value": 0.59,
      "count": 1,
      "provenance": {
        "source": "jobtech:jobsearch",
        "period": "2026-06-16",
        "fetched": "2026-06-16"
      }
    },
    "MVqp_eS8_kDZ": {
      "label": "Pedagogik",
      "value": 2.95,
      "count": 5,
      "provenance": {
        "source": "jobtech:jobsearch",
        "period": "2026-06-16",
        "fetched": "2026-06-16"
      }
    },
    "whao_Q6A_ScE": {
      "label": "Sanering och renhållning",
      "value": 1.18,
      "count": 2,
      "provenance": {
        "source": "jobtech:jobsearch",
        "period": "2026-06-16",
        "fetched": "2026-06-16"
      }
    },
    "apaJ_2ja_LuF": {
      "label": "Data/IT",
      "value": 1.18,
      "count": 2,
      "provenance": {
        "source": "jobtech:jobsearch",
        "period": "2026-06-16",
        "fetched": "2026-06-16"
      }
    },
    "ScKy_FHB_7wT": {
      "label": "Hotell, restaurang, storhushåll",
      "value": 1.18,
      "count": 2,
      "provenance": {
        "source": "jobtech:jobsearch",
        "period": "2026-06-16",
        "fetched": "2026-06-16"
      }
    },
    "6Hq3_tKo_V57": {
      "label": "Yrken med teknisk inriktning",
      "value": 0.59,
      "count": 1,
      "provenance": {
        "source": "jobtech:jobsearch",
        "period": "2026-06-16",
        "fetched": "2026-06-16"
      }
    },
    "j7Cq_ZJe_GkT": {
      "label": "Bygg och anläggning",
      "value": 0.59,
      "count": 1,
      "provenance": {
        "source": "jobtech:jobsearch",
        "period": "2026-06-16",
        "fetched": "2026-06-16"
      }
    },
    "bh3H_Y3h_5eD": {
      "label": "Chefer och verksamhetsledare",
      "value": 0.59,
      "count": 1,
      "provenance": {
        "source": "jobtech:jobsearch",
        "period": "2026-06-16",
        "fetched": "2026-06-16"
      }
    }
  },
  "energy": {
    "price_area": "SE3",
    "price_level": {
      "value": 76.42,
      "provenance": {
        "source": "elprisetjustnu:spot;zones:electricitymaps/entsoe",
        "period": "trailing-30d",
        "fetched": "2026-06-17"
      }
    }
  },
  "safety": {
    "reported_crime_per_100k": {
      "value": 4740.00707,
      "provenance": {
        "source": "kolada:N07540",
        "period": 2025
      }
    }
  },
  "schools": {
    "eligibility_pct": {
      "value": 86.4,
      "provenance": {
        "source": "kolada:N15424",
        "period": 2025
      }
    }
  }
}